__init__.py
flattenKern.py
sameWidther.py
databases/ENG.json
databases/GER.json
databases/__init__.py
sameWidther-0.0.5.dist-info/METADATA
sameWidther-0.0.5.dist-info/WHEEL
sameWidther-0.0.5.dist-info/entry_points.txt
sameWidther-0.0.5.dist-info/top_level.txt
sameWidther-0.0.5.dist-info/RECORD
