Metadata-Version: 2.1
Name: sameWidther
Version: 0.0.5
Summary: Gets random words of the same width for given font
Home-page: https://github.com/jansindl3r/sameWidther
Author: Jan Šindler
Author-email: jansindl3r@gmail.com
License: MIT
Keywords: font typography graphicdesign specimen width word
Platform: UNKNOWN
Requires-Python: >=3.6
Requires-Dist: defcon (>=0.6.0)
Requires-Dist: fonttools (>=3.31.0)
